paramctl/__init__.py
paramctl/paramctl.py
paramctl-0.55.dist-info/DESCRIPTION.rst
paramctl-0.55.dist-info/METADATA
paramctl-0.55.dist-info/RECORD
paramctl-0.55.dist-info/WHEEL
paramctl-0.55.dist-info/metadata.json
paramctl-0.55.dist-info/top_level.txt
